nona/__init__.py
nona/nona.py
nona-0.0.2.dist-info/LICENSE
nona-0.0.2.dist-info/METADATA
nona-0.0.2.dist-info/WHEEL
nona-0.0.2.dist-info/top_level.txt
nona-0.0.2.dist-info/RECORD
