Metadata-Version: 2.1
Name: nona
Version: 0.0.2
Summary: Python gap filling toolkit
Home-page: https://github.com/AbdualimovTP/nona
Author: Timur Abdualimov
Author-email: timur.atp@yandex.ru
Classifier: Programming Language :: Python :: 3.10
Classifier: License :: OSI Approved :: GNU General Public License v3 (GPLv3)
License-File: LICENSE
Requires-Dist: pandas (>=1)
Requires-Dist: numpy (>=1)
Requires-Dist: scikit-learn (>=1)
Requires-Dist: tqdm (>=4)
